greydata/__init__.py
greydata/arguments.py
greydata/cli.py
greydata/module1.py
greydata/module2.py
greydata/welcome.py
greydata/data_analyst/__init__.py
greydata/data_analyst/module_code.py
greydata/data_engineer/__init__.py
greydata/data_engineer/crud_ui.py
greydata/data_engineer/database.py
greydata/data_engineer/module_code.py
greydata/data_engineer/system.py
greydata/data_scientist/__init__.py
greydata/data_scientist/module_code.py
greydata-0.2.2.dist-info/LICENSE
greydata-0.2.2.dist-info/METADATA
greydata-0.2.2.dist-info/WHEEL
greydata-0.2.2.dist-info/entry_points.txt
greydata-0.2.2.dist-info/top_level.txt
greydata-0.2.2.dist-info/RECORD
